Verilog/iverilog/4-Bit Synchronous Counter/syn_counter.v
module syn_counter (
	input wire clk,rst,
	output reg [3:0]count
);

always @(posedge clk) begin
	if (rst) 
		count<= 4'b000;
	else
		count<=count+1'b1;
end

endmodule

Verilog/iverilog/4-Bit Synchronous Counter/tb_syn_counter.v
module tb_syn_counter;

reg clk,rst;
wire [3:0]count;

syn_counter DUT (
	.clk(clk),
	.rst(rst),
	.count(count)
);

always #5 clk=~clk;

initial begin
	clk=0;rst=1;
#10 rst=0;
#200 $finish;

end

initial begin
    $dumpfile("dump.vcd");
    $dumpvars(0, tb_syn_counter);
end

endmodule

Verilog/iverilog/4-Bit Synchronous Counter/dump.vcd
$date
	Fri Jan 02 08:48:38 2026
$end
$version
	Icarus Verilog
$end
$timescale
	1s
$end
$scope module tb_syn_counter $end
$var wire 4 ! count [3:0] $end
$var reg 1 " clk $end
$var reg 1 # rst $end
$scope module DUT $end
$var wire 1 " clk $end
$var wire 1 # rst $end
$var reg 4 $ count [3:0] $end
$upscope $end
$upscope $end
$enddefinitions $end
#0
$dumpvars
bx $
1#
0"
bx !
$end
#5
b0 !
b0 $
1"
#10
0"
0#
#15
b1 !
b1 $
1"
#20
0"
#25
b10 !
b10 $
1"
#30
0"
#35
b11 !
b11 $
1"
#40
0"
#45
b100 !
b100 $
1"
#50
0"
#55
b101 !
b101 $
1"
#60
0"
#65
b110 !
b110 $
1"
#70
0"
#75
b111 !
b111 $
1"
#80
0"
#85
b1000 !
b1000 $
1"
#90
0"
#95
b1001 !
b1001 $
1"
#100
0"
#105
b1010 !
b1010 $
1"
#110
0"
#115
b1011 !
b1011 $
1"
#120
0"
#125
b1100 !
b1100 $
1"
#130
0"
#135
b1101 !
b1101 $
1"
#140
0"
#145
b1110 !
b1110 $
1"
#150
0"
#155
b1111 !
b1111 $
1"
#160
0"
#165
b0 !
b0 $
1"
#170
0"
#175
b1 !
b1 $
1"
#180
0"
#185
b10 !
b10 $
1"
#190
0"
#195
b11 !
b11 $
1"
#200
0"
#205
b100 !
b100 $
1"
