Verilog/iverilog/Practice/Sequence Detector FSM (Moore)/seq_101.v
module seq_101 (
	input wire clk,rst,in,
	output reg out
);

parameter [1:0] s0=2'b00,
				s1=2'b01,
				s2=2'b10,
				s3=2'b11;
				
reg [1:0] state, next_state;

always @(posedge clk) begin
	if(rst)
		state<=s0;
	else
		state<=next_state;
end

always @(*) begin
	case (state)
		s0: next_state=in?s1:s0;
		s1: next_state=in?s1:s2;
		s2: next_state=in?s3:s0;
		s3: next_state=in?s1:s0;
		default: next_state=s0;
	endcase
end

always @(*) begin
	out = (state == s3);
end

endmodule

Verilog/iverilog/Practice/Sequence Detector FSM (Moore)/tb_seq_101.v
module tb_seq_101;

reg clk,rst,in;
wire out;

seq_101 DUT (
	.clk(clk),
	.rst(rst),
	.in(in),
	.out(out)
);

always #5 clk=~clk;

initial begin
	clk=0;rst=1;in=0;
#10 rst=0;

#10 in=1;
#10 in=0;
#10 in=1;
#10 in=0;

$display("time=%0t in=%b out=%b", $time, in, out);


#20 $finish;

end

initial begin
    $dumpfile("wave.vcd");
    $dumpvars(0, tb_seq_101);
end

endmodule

Verilog/iverilog/Practice/Sequence Detector FSM (Moore)/wave.vcd
$date
	Fri Jan 02 12:33:02 2026
$end
$version
	Icarus Verilog
$end
$timescale
	1s
$end
$scope module tb_seq_101 $end
$var wire 1 ! out $end
$var reg 1 " clk $end
$var reg 1 # in $end
$var reg 1 $ rst $end
$scope module DUT $end
$var wire 1 " clk $end
$var wire 1 # in $end
$var wire 1 $ rst $end
$var reg 2 % next_state [1:0] $end
$var reg 1 ! out $end
$var reg 2 & state [1:0] $end
$upscope $end
$upscope $end
$enddefinitions $end
#0
$dumpvars
bx &
b0 %
1$
0#
0"
x!
$end
#5
0!
b0 &
1"
#10
0"
0$
#15
1"
#20
b1 %
0"
1#
#25
b1 &
1"
#30
b10 %
0"
0#
#35
b0 %
b10 &
1"
#40
b11 %
0"
1#
#45
1!
b1 %
b11 &
1"
#50
b0 %
0"
0#
#55
0!
b0 &
1"
